[
  {
    "autor": "Mariana Duarte",
    "texto": "Trilha Exploradora 360 tem uma escuta ativa rara e sempre devolve feedbacks práticos.",
    "email": "mariana.duarte@example.com",
    "data": "25/10/2024, 12:02:00"
  },
  {
    "autor": "Ana Beatriz",
    "texto": "Os materiais de apoio de Trilha Exploradora 360 continuam sendo referência no capítulo.",
    "email": "ana.beatriz@example.com",
    "data": "25/10/2024, 12:05:00"
  },
  {
    "autor": "Talita Campos",
    "texto": "Foi incrível ver o tanto que Trilha Exploradora 360 aproxima áreas diferentes sem criar atrito.",
    "email": "talita.campos@example.com",
    "data": "25/10/2024, 12:09:00"
  },
  {
    "autor": "Igor Martins",
    "texto": "Trilha Exploradora 360 trouxe uma visão estratégica que faltava e deixou planos bem estruturados.",
    "email": "igor.martins@example.com",
    "data": "25/10/2024, 12:11:00"
  },
  {
    "autor": "Olívia Prado",
    "texto": "As sessões com Trilha Exploradora 360 renovam a energia da equipe e geram decisões rápidas.",
    "email": "olivia.prado@example.com",
    "data": "25/10/2024, 12:13:00"
  },
  {
    "autor": "Teste",
    "texto": "Teste",
    "email": "daniel.kodeout@gmail.com",
    "data": "23/09/2025, 19:28:31"
  },
  {
    "autor": "QWay",
    "texto": "Teste",
    "email": "contato@qway.com.br",
    "data": "02/11/2025, 19:02:18"
  }
]