{
  "ambiente": "demo",
  "ultimaAtualizacao": "2026-02-23T05:51:46.163Z",
  "quantidade_total": 62,
  "mais_curtidas": [
    "pos-9989",
    "pos-9974",
    "pos-9995",
    "pos-9987",
    "pos-9996",
    "pos-9994"
  ],
  "mais_comentadas": [
    "pos-9974",
    "pos-9989",
    "pos-9988",
    "pos-9987",
    "neg-9977",
    "pos-9972"
  ],
  "mais_recentes": [
    "pos-9999",
    "neg-9999",
    "pos-9998",
    "neg-9998",
    "pos-9997",
    "neg-9997"
  ],
  "totais": {
    "positivas": 32,
    "negativas": 30
  },
  "totais_por_tipo": {
    "profissional": {
      "positivas": 5,
      "negativas": 5
    },
    "empresa": {
      "positivas": 5,
      "negativas": 5
    },
    "educacao": {
      "positivas": 5,
      "negativas": 5
    },
    "conteudo": {
      "positivas": 6,
      "negativas": 5
    },
    "comunidade": {
      "positivas": 6,
      "negativas": 5
    },
    "evento": {
      "positivas": 5,
      "negativas": 5
    }
  }
}